<?xml version="1.0" encoding='UTF-8'?>
<results algorithmName="GS" algorithmVersion="101001" time="9:00" date="2013">
<query content="author:&quot;Aobo Wang&quot; NUS" label="" count="2" totalresults="2">
  <result id="0">
    <url>http://www.aclweb.org/anthology/W12-21#page=56</url>
    <title status="complete" source="scholar.google.com">Re-tweeting from a Linguistic Perspective</title>
    <pdf>http://www.aclweb.org/anthology/W12-21#page=56</pdf>
    <author status="complete" source="scholar.google.com">A Wang, T Chen, MY Kan</author>
    <proceeding status="complete" source="scholar.google.com">NAACL-HLT 2012</proceeding>
    <year>2012</year>
    <source>aclweb.org</source>
    <snippet status="partial" source="scholar.google.com">... cO2012 Association for Computational Linguistics Re-tweeting from a Linguistic Perspective AoboWang Tao Chen Web IR/NLP Group (WING) National University of Singapore 13 Computing Link,Singapore 117590 {wangaobo, taochen, kanmy}@ comp. nus. edu. ...</snippet>
    <relatedLink>http://scholar.google.com.sg/scholar?q=related:fb8YhGrXvIoJ:scholar.google.com/&amp;hl=en&amp;num=100&amp;as_sdt=1,5&amp;as_vis=1</relatedLink>
    <htmlLink>http://scholar.googleusercontent.com/scholar?q=cache:fb8YhGrXvIoJ:scholar.google.com/+author:%22Aobo+Wang%22+NUS&amp;hl=en&amp;num=100&amp;as_sdt=1,5&amp;as_vis=1</htmlLink>
    <numVersions>29</numVersions>
    <versionLink>http://scholar.google.com.sg/scholar?cluster=9997102125338378109&amp;hl=en&amp;num=100&amp;as_sdt=1,5&amp;as_vis=1</versionLink>
    <numCite>2</numCite>
    <citeLink>http://scholar.google.com.sg/scholar?cites=9997102125338378109&amp;as_sdt=2005&amp;sciodt=1,5&amp;hl=en&amp;num=100</citeLink>
    <citedBy totalresults="2">
        <result id="0">
        <url>http://www.springerlink.com/index/974N72210211201T.pdf</url>
        <title status="complete" source="scholar.google.com">Creating a live, public short message service corpus: The NUS SMS corpus</title>
        <pdf>http://arxiv.org/pdf/1112.2468</pdf>
        <author status="complete" source="scholar.google.com">T Chen, MY Kan</author>
        <proceeding status="complete" source="scholar.google.com">Language Resources and Evaluation</proceeding>
        <year>2011</year>
        <source>Springer</source>
        <snippet status="partial" source="scholar.google.com">Abstract Short Message Service (SMS) messages are short messages sent from one person to another from their mobile phones. They represent a means of personal communication that is an important communicative artifact in our current digital era. As most existing ...</snippet>
        <relatedLink>http://scholar.google.com.sg/scholar?q=related:MzUcR-66-EAJ:scholar.google.com/&amp;hl=en&amp;num=2&amp;as_sdt=0,5&amp;sciodt=0,5</relatedLink>
        <numVersions>20</numVersions>
        <versionLink>http://scholar.google.com.sg/scholar?cluster=4681697345209644339&amp;hl=en&amp;num=2&amp;as_sdt=0,5&amp;sciodt=0,5</versionLink>
        <numCite>5</numCite>
        <citeLink>http://scholar.google.com.sg/scholar?cites=4681697345209644339&amp;as_sdt=2005&amp;sciodt=0,5&amp;hl=en&amp;num=2</citeLink>
        <citedBy totalresults="0">
        </citedBy>
      </result>
      <result id="1">
        <url>http://dl.acm.org/citation.cfm?id=2398519</url>
        <title status="complete" source="scholar.google.com">Discover breaking events with popular hashtags in twitter</title>
        <author status="complete" source="scholar.google.com">A Cui, M Zhang, Y Liu, S Ma, K Zhang</author>
        <proceeding status="partial" source="scholar.google.com">Proceedings of the 21st ACM &#8230;</proceeding>
        <year>2012</year>
        <source>dl.acm.org</source>
        <snippet status="partial" source="scholar.google.com">Abstract In this paper, we utilize tags in Twitter (the hashtags) as an indicator of events. We first study the properties of hashtags for event detection. Based on several observations, we proposed three attributes of hashtags, including (1) instability for temporal analysis,(2) ...</snippet>
        <citedBy totalresults="0">
        </citedBy>
      </result>
    </citedBy>
  </result>
  <result id="1">
    <url>http://www.springerlink.com/index/N5Q5N08853T06131.pdf</url>
    <title status="complete" source="scholar.google.com">Perspectives on crowdsourcing annotations for natural language processing</title>
    <pdf>http://dl.comp.nus.edu.sg/dspace/bitstream/1900.100/3266/1/TRB7-10.pdf</pdf>
    <author status="complete" source="scholar.google.com">A Wang, CDV Hoang, MY Kan</author>
    <proceeding status="complete" source="scholar.google.com">Language Resources and Evaluation</proceeding>
    <year>2010</year>
    <source>Springer</source>
    <snippet status="partial" source="scholar.google.com">... Aobo Wang • Cong Duy Vu Hoang • Min-Yen Kan Ó Springer Science+Business Media BV2012 ... A. Wang AS6 04-13 Computing 1, 13 Computing Drive National University of Singapore,Singapore 117417, Singapore e-mail: wangaobo@comp.nus.edu.sg ...</snippet>
    <relatedLink>http://scholar.google.com.sg/scholar?q=related:YUhwnlhfnnUJ:scholar.google.com/&amp;hl=en&amp;num=100&amp;as_sdt=1,5&amp;as_vis=1</relatedLink>
    <numVersions>26</numVersions>
    <versionLink>http://scholar.google.com.sg/scholar?cluster=8475316382977771617&amp;hl=en&amp;num=100&amp;as_sdt=1,5&amp;as_vis=1</versionLink>
    <citedBy totalresults="0">
    </citedBy>
  </result>
</query>
</results>
